ansys/scade/pyhg/__init__.py
ansys/scade/pyhg/proxy_thg.py
ansys/scade/pyhg/pyhg.py
ansys/scade/pyhg/pyhg.srg
ansys/scade/pyhg/settings.py
ansys/scade/pyhg/values.py
ansys/scade/pyhg/lib/run.py
ansys/scade/pyhg/lib/thgrt.py
ansys_scade_pyhg-2.1.0.dist-info/entry_points.txt
ansys_scade_pyhg-2.1.0.dist-info/LICENSE
ansys_scade_pyhg-2.1.0.dist-info/WHEEL
ansys_scade_pyhg-2.1.0.dist-info/METADATA
ansys_scade_pyhg-2.1.0.dist-info/RECORD
