Metadata-Version: 2.3
Name: ansys-scade-pyhg
Version: 2.1.0
Summary: SCADE Test Harness Generator for Python.
Keywords: Scade,Test,Harness
Author-email: "ANSYS, Inc." <pyansys.core@ansys.com>
Maintainer-email: "ANSYS, Inc." <pyansys.core@ansys.com>
Requires-Python: >=3.10,<3.11
Classifier: Development Status :: 4 - Beta
Classifier: Programming Language :: Python :: 3
Classifier: License :: OSI Approved :: MIT License
Classifier: Operating System :: Microsoft :: Windows
Requires-Dist: ansys-scade-apitools
Requires-Dist: pyparsing
Requires-Dist: build==1.2.2.post1 ; extra == "build"
Requires-Dist: twine==5.1.1 ; extra == "build"
Requires-Dist: ansys-sphinx-theme[autoapi]==1.1.2 ; extra == "doc"
Requires-Dist: jupyter_sphinx==0.5.3 ; extra == "doc"
Requires-Dist: nbsphinx==0.9.5 ; extra == "doc"
Requires-Dist: numpydoc==1.8.0 ; extra == "doc"
Requires-Dist: sphinx==8.0.2 ; extra == "doc"
Requires-Dist: sphinx-autodoc-typehints==2.3.0 ; extra == "doc"
Requires-Dist: sphinxcontrib-globalsubs==0.1.2 ; extra == "doc"
Requires-Dist: sphinxcontrib-httpdomain==1.8.1 ; extra == "doc"
Requires-Dist: sphinx-copybutton==0.5.2 ; extra == "doc"
Requires-Dist: pytest==8.0.2 ; extra == "tests"
Requires-Dist: pytest-cov==5.0.0 ; extra == "tests"
Project-URL: Discussions, https://github.com/ansys/scade-pyhg/discussions
Project-URL: Documentation, https://pyhg.scade.docs.pyansys.com
Project-URL: Homepage, https://www.ansys.com/products/embedded-software/ansys-scade-suite
Project-URL: Issues, https://github.com/ansys/scade-pyhg/issues
Project-URL: Releases, https://github.com/ansys/scade-pyhg/releases
Project-URL: Source, https://github.com/ansys/scade-pyhg
Provides-Extra: build
Provides-Extra: doc
Provides-Extra: tests
